jupyterlab_vim/__init__.py
jupyterlab_vim/_version.py
jupyterlab_vim/labextension/package.json
jupyterlab_vim/labextension/schemas/@ryantam626/jupyterlab_vim/package.json.orig
jupyterlab_vim/labextension/schemas/@ryantam626/jupyterlab_vim/plugin.json
jupyterlab_vim/labextension/static/style.js
ryantam626_jupyterlab_vim-0.16.2.data/data/share/jupyter/labextensions/@ryantam626/jupyterlab_vim/install.json
ryantam626_jupyterlab_vim-0.16.2.data/data/share/jupyter/labextensions/@ryantam626/jupyterlab_vim/package.json
ryantam626_jupyterlab_vim-0.16.2.data/data/share/jupyter/labextensions/@ryantam626/jupyterlab_vim/schemas/@ryantam626/jupyterlab_vim/package.json.orig
ryantam626_jupyterlab_vim-0.16.2.data/data/share/jupyter/labextensions/@ryantam626/jupyterlab_vim/schemas/@ryantam626/jupyterlab_vim/plugin.json
ryantam626_jupyterlab_vim-0.16.2.data/data/share/jupyter/labextensions/@ryantam626/jupyterlab_vim/static/style.js
ryantam626_jupyterlab_vim-0.16.2.dist-info/LICENSE
ryantam626_jupyterlab_vim-0.16.2.dist-info/METADATA
ryantam626_jupyterlab_vim-0.16.2.dist-info/WHEEL
ryantam626_jupyterlab_vim-0.16.2.dist-info/top_level.txt
ryantam626_jupyterlab_vim-0.16.2.dist-info/RECORD
